poetry_plugin_ivcap/constants.py
poetry_plugin_ivcap/docker.py
poetry_plugin_ivcap/ivcap.py
poetry_plugin_ivcap/plugin.py
poetry_plugin_ivcap/types.py
poetry_plugin_ivcap/util.py
poetry_plugin_ivcap-0.5.2.dist-info/AUTHORS.md
poetry_plugin_ivcap-0.5.2.dist-info/LICENSE
poetry_plugin_ivcap-0.5.2.dist-info/METADATA
poetry_plugin_ivcap-0.5.2.dist-info/WHEEL
poetry_plugin_ivcap-0.5.2.dist-info/entry_points.txt
poetry_plugin_ivcap-0.5.2.dist-info/RECORD
