Metadata-Version: 2.3
Name: poetry-plugin-ivcap
Version: 0.5.2
Summary: A custom Poetry command for IVCAP deployments
License: MIT
Author: Max Ott
Author-email: max.ott@csiro.au
Requires-Python: >=3.9
Classifier: License :: OSI Approved :: MIT License
Classifier: Programming Language :: Python :: 3
Classifier: Programming Language :: Python :: 3.9
Classifier: Programming Language :: Python :: 3.10
Classifier: Programming Language :: Python :: 3.11
Classifier: Programming Language :: Python :: 3.12
Classifier: Programming Language :: Python :: 3.13
Requires-Dist: humanize (>=4.12.3,<5.0.0)
Requires-Dist: pydantic (>=2.11.5,<3.0.0)
